chaosreliably/__init__.py
chaosreliably/__version__.py
chaosreliably/activities/__init__.py
chaosreliably/activities/dns/__init__.py
chaosreliably/activities/dns/probes.py
chaosreliably/activities/dns/tolerances.py
chaosreliably/activities/gh/__init__.py
chaosreliably/activities/gh/actions.py
chaosreliably/activities/gh/probes.py
chaosreliably/activities/gh/tolerances.py
chaosreliably/activities/http/__init__.py
chaosreliably/activities/http/probes.py
chaosreliably/activities/http/tolerances.py
chaosreliably/activities/load/__init__.py
chaosreliably/activities/load/actions.py
chaosreliably/activities/load/probes.py
chaosreliably/activities/load/scripts/__init__.py
chaosreliably/activities/load/scripts/step_load_test.py
chaosreliably/activities/pauses.py
chaosreliably/activities/safeguard/__init__.py
chaosreliably/activities/safeguard/probes.py
chaosreliably/activities/slo/__init__.py
chaosreliably/activities/slo/probes.py
chaosreliably/activities/slo/tolerances.py
chaosreliably/activities/tls/__init__.py
chaosreliably/activities/tls/probes.py
chaosreliably/activities/tls/tolerances.py
chaosreliably/controls/__init__.py
chaosreliably/controls/autopause.py
chaosreliably/controls/capture/__init__.py
chaosreliably/controls/capture/slack.py
chaosreliably/controls/chatgpt.py
chaosreliably/controls/experiment.py
chaosreliably/controls/metrics.py
chaosreliably/controls/prechecks.py
chaosreliably/controls/safeguard.py
chaosreliably/controls/vendors/__init__.py
chaosreliably/controls/vendors/honeycomb.py
chaosreliably/controls/vendors/otel.py
chaosreliably/py.typed
chaosreliably/types.py
chaostoolkit_reliably-0.82.0.dist-info/METADATA
chaostoolkit_reliably-0.82.0.dist-info/WHEEL
chaostoolkit_reliably-0.82.0.dist-info/entry_points.txt
chaostoolkit_reliably-0.82.0.dist-info/licenses/LICENSE
chaostoolkit_reliably-0.82.0.dist-info/RECORD
