Metadata-Version: 2.1
Name: chaostoolkit-reliably
Version: 0.82.0
Summary: Reliably CLI
Author-Email: Chaos Toolkit <contact@chaostoolkit.org>
License: Apache-2.0
Classifier: Development Status :: 4 - Beta
Classifier: Intended Audience :: Developers
Classifier: License :: Freely Distributable
Classifier: License :: OSI Approved :: Apache Software License
Classifier: Operating System :: OS Independent
Classifier: Programming Language :: Python
Classifier: Programming Language :: Python :: 3
Classifier: Programming Language :: Python :: 3.9
Classifier: Programming Language :: Python :: 3.10
Classifier: Programming Language :: Python :: 3.11
Classifier: Programming Language :: Python :: 3.12
Classifier: Programming Language :: Python :: Implementation
Classifier: Programming Language :: Python :: Implementation :: CPython
Project-URL: documentation, https://chaostoolkit.org
Project-URL: repository, https://github.com/chaostoolkit-incubator/chaostoolkit-reliably
Project-URL: changelog, https://github.com/chaostoolkit-incubator/chaostoolkit-reliably/blob/master/CHANGELOG.md
Requires-Python: !=3.9.1,>3.9.0
Requires-Dist: chaostoolkit-lib>=1.34.1
Requires-Dist: httpx[http2]>=0.23.3
Requires-Dist: cryptography>=39.0.2
Requires-Dist: boltons>=23.0.0
Requires-Dist: locust>=2.15.0
Requires-Dist: slo-generator[cloud_monitoring,datadog,dynatrace,prometheus]>=2.3.4
Requires-Dist: chaostoolkit-addons>=0.4.0
Requires-Dist: orjson>=3.8.10
Requires-Dist: dnspython>=2.3.0
Requires-Dist: grpcio>=1.64.1
Provides-Extra: dev
Requires-Dist: black>=22.10.0; extra == "dev"
Requires-Dist: isort>=5.10.1; extra == "dev"
Requires-Dist: pytest>=7.2.0; extra == "dev"
Requires-Dist: coverage>=6.5.0; extra == "dev"
Requires-Dist: pytest-cov>=4.0.0; extra == "dev"
Requires-Dist: pytest-sugar>=0.9.5; extra == "dev"
Requires-Dist: ruff>=0.0.253; extra == "dev"
Requires-Dist: mypy>=1.0.1; extra == "dev"
Requires-Dist: bandit>=1.7.4; extra == "dev"
Requires-Dist: respx>=0.20.1; extra == "dev"
